checkdocs/__init__.py
checkdocs/checkers/__init__.py
checkdocs/checkers/check_file.py
checkdocs/checkers/check_folder.py
checkdocs/checkers/make_check.py
checkdocs/config/__init__.py
checkdocs/config/config.py
checkdocs/main.py
checkdocs/printers.py
checkdocs-0.1.1.dist-info/entry_points.txt
checkdocs-0.1.1.dist-info/LICENSE
checkdocs-0.1.1.dist-info/METADATA
checkdocs-0.1.1.dist-info/WHEEL
checkdocs-0.1.1.dist-info/RECORD
